torch_track/__init__.py
torch_track/track_functions.py
TorchTrack-0.1.3.dist-info/METADATA
TorchTrack-0.1.3.dist-info/WHEEL
TorchTrack-0.1.3.dist-info/top_level.txt
TorchTrack-0.1.3.dist-info/RECORD
