Metadata-Version: 2.1
Name: TorchTrack
Version: 0.1.3
Summary: TorchTrack takes your models data and training data then send it to the TrackML web application
Author: NeuralNuts
